oneNeuron/__init__.py
oneNeuron/perceptron.py
Perceptron_ashishjang-0.0.1.dist-info/LICENSE
Perceptron_ashishjang-0.0.1.dist-info/METADATA
Perceptron_ashishjang-0.0.1.dist-info/WHEEL
Perceptron_ashishjang-0.0.1.dist-info/top_level.txt
Perceptron_ashishjang-0.0.1.dist-info/RECORD
